[
    {"id":000,"family":"style","name":"Molding Gel","descrition-01":"Gel a tenuta forte per capelli","descrition-02":"Gel a tenuta forte. Modella e definisce. Adatto a tutti i tipi di capello. Non unge e non lascia residui. Arricchito da estratto di zenzero e ginseng è un vero mix di sostanze energizzanti e stimolanti. La sua fragranza, risultato di note fruttate, floreali e un fondo esotico e maschile, inebria e avvolge a lungo.","formato":"200 ml","ingredienti":"Estratto di zenzero","PH":6.2,"NeN":"PARABEN, PETROLATUM, MINERAL OIL, COLORANT","image":"./img-prod/man-MG"},
    {"id":001,"family":"style","name":"Sculpting Gel","descrition-01":"Gel per capelli a tenuta extra forte","descrition-02":"Gel a tenuta extra forte. Scolpisce e fissa. Adatto a tutti i tipi di capello. Non unge e non lascia residui. Arricchito da estratto di zenzero e ginseng è un vero mix di sostanze energizzanti e stimolanti. La sua fragranza, risultato di note fruttate, floreali e un fondo esotico e maschile, inebria e avvolge a lungo.","formato":"200 ml","ingredienti":"Estratto di zenzero e ginseng","PH":6.3,"NeN":"PARABEN, PETROLATUM, MINERAL OIL, COLORANT","image":"./img-prod/man-MG"}]